libmonty_logging/__init__.py
libmonty_logging/configs.py
libmonty_logging/formatters.py
libmonty_logging/handlers.py
libmonty_logging/message.py
libmonty_logging/paths.py
libmonty_logging/version.py
libmonty_logging-0.3.0.dist-info/LICENSE
libmonty_logging-0.3.0.dist-info/METADATA
libmonty_logging-0.3.0.dist-info/WHEEL
libmonty_logging-0.3.0.dist-info/top_level.txt
libmonty_logging-0.3.0.dist-info/RECORD
