Metadata-Version: 2.1
Name: libmonty-logging
Version: 0.3.0
Summary: libmonty-logging - Python library - logging-related
Home-page: https://codeberg.org/sunarch/libmonty-logging
Author: András Németh (sunarch)
Author-email: sunarch@protonmail.com
Maintainer: András Németh (sunarch)
Maintainer-email: sunarch@protonmail.com
License: Mozilla Public License 2.0 (MPL 2.0)
Project-URL: Bug Tracker, https://codeberg.org/sunarch/libmonty-logging/issues
Keywords: libmonty,logging
Platform: Any
Classifier: Programming Language :: Python :: 3
Classifier: Natural Language :: English
Classifier: License :: OSI Approved :: Mozilla Public License 2.0 (MPL 2.0)
Classifier: Operating System :: OS Independent
Classifier: Development Status :: 3 - Alpha
Classifier: Environment :: Console
Classifier: Intended Audience :: Developers
Classifier: Topic :: Software Development :: Libraries
Classifier: Topic :: System :: Logging
Classifier: Typing :: Typed
Requires-Python: >=3.9
License-File: LICENSE
Requires-Dist: xdg-base-dirs ==6.0.1
